{
    "image_url_template": "https://www.toyota.com/imgix/responsive/images/mlp/colorizer/{YEAR}/{MODEL_SLUG}/{COLOR_CODE}/1.png",
    "image_notes": "PNG with transparent background from Toyota's build-studio colorizer. Replace {YEAR}, {MODEL_SLUG} (e.g., camry, corolla-hatchback, rav4-prime), and {COLOR_CODE} (e.g., 040 = Super White, 218 = Black, 1L5 = Underground). Angle index '1' is a 3/4 studio view; use 0–7 for other angles.",
    "vehicles": [
      {
        "year": 2025,
        "make": "Toyota",
        "model": "Camry",
        "trim": "LE (Hybrid)",
        "msrp_usd": 28400,
        "horsepower_hp": 225,
        "drivetrain": "FWD (AWD optional)",
        "fuel": "Hybrid",
        "transmission": "eCVT",
        "body_style": "Sedan",
        "mpg_combined_est": 51,
        "image_url": "https://www.toyota.com/imgix/responsive/images/mlp/colorizer/2025/camry/1L5/1.png"
      },
      {
        "year": 2025,
        "make": "Toyota",
        "model": "Corolla",
        "trim": "LE",
        "msrp_usd": 22000,
        "horsepower_hp": 169,
        "drivetrain": "FWD",
        "fuel": "Gasoline",
        "transmission": "CVT",
        "body_style": "Sedan",
        "mpg_combined_est": 35,
        "image_url": "https://www.toyota.com/imgix/responsive/images/mlp/colorizer/2025/corolla/1L5/1.png"
      },
      {
        "year": 2025,
        "make": "Toyota",
        "model": "Corolla Hybrid",
        "trim": "LE",
        "msrp_usd": 23950,
        "horsepower_hp": 138,
        "drivetrain": "FWD (AWD optional)",
        "fuel": "Hybrid",
        "transmission": "eCVT",
        "body_style": "Sedan",
        "mpg_combined_est": 50,
        "image_url": "https://www.toyota.com/imgix/responsive/images/mlp/colorizer/2025/corolla-hybrid/1L5/1.png"
      },
      {
        "year": 2025,
        "make": "Toyota",
        "model": "Corolla Hatchback",
        "trim": "SE",
        "msrp_usd": 23500,
        "horsepower_hp": 168,
        "drivetrain": "FWD",
        "fuel": "Gasoline",
        "transmission": "CVT",
        "body_style": "Hatchback",
        "mpg_combined_est": 33,
        "image_url": "https://www.toyota.com/imgix/responsive/images/mlp/colorizer/2025/corolla-hatchback/1L5/1.png"
      },
      {
        "year": 2024,
        "make": "Toyota",
        "model": "Prius",
        "trim": "LE (FWD)",
        "msrp_usd": 27850,
        "horsepower_hp": 194,
        "drivetrain": "FWD (AWD optional)",
        "fuel": "Hybrid",
        "transmission": "eCVT",
        "body_style": "Liftback",
        "mpg_combined_est": 57,
        "image_url": "https://www.toyota.com/imgix/responsive/images/mlp/colorizer/2024/prius/1L5/1.png"
      },
      {
        "year": 2024,
        "make": "Toyota",
        "model": "Prius Prime",
        "trim": "SE (PHEV)",
        "msrp_usd": 32975,
        "horsepower_hp": 220,
        "drivetrain": "FWD",
        "fuel": "Plug-in Hybrid",
        "transmission": "eCVT",
        "body_style": "Liftback",
        "ev_range_mi_est": 44,
        "image_url": "https://www.toyota.com/imgix/responsive/images/mlp/colorizer/2024/prius-prime/1L5/1.png"
      },
      {
        "year": 2025,
        "make": "Toyota",
        "model": "Crown",
        "trim": "XLE (Hybrid Max varies by trim)",
        "msrp_usd": 40500,
        "horsepower_hp": 236,
        "drivetrain": "AWD",
        "fuel": "Hybrid",
        "transmission": "eCVT",
        "body_style": "Sedan",
        "mpg_combined_est": 41,
        "image_url": "https://www.toyota.com/imgix/responsive/images/mlp/colorizer/2025/crown/1L5/1.png"
      },
      {
        "year": 2025,
        "make": "Toyota",
        "model": "Crown Signia",
        "trim": "XLE (Hybrid)",
        "msrp_usd": 44090,
        "horsepower_hp": 243,
        "drivetrain": "AWD",
        "fuel": "Hybrid",
        "transmission": "eCVT",
        "body_style": "SUV",
        "mpg_combined_est": 39,
        "image_url": "https://www.toyota.com/imgix/responsive/images/mlp/colorizer/2025/crown-signia/1L5/1.png"
      },
      {
        "year": 2024,
        "make": "Toyota",
        "model": "GR86",
        "trim": "Base (MT)",
        "msrp_usd": 28900,
        "horsepower_hp": 228,
        "drivetrain": "RWD",
        "fuel": "Gasoline",
        "transmission": "6MT",
        "body_style": "Coupe",
        "image_url": "https://www.toyota.com/imgix/responsive/images/mlp/colorizer/2024/gr86/1L5/1.png"
      },
      {
        "year": 2024,
        "make": "Toyota",
        "model": "GR Supra",
        "trim": "2.0",
        "msrp_usd": 46165,
        "horsepower_hp": 255,
        "drivetrain": "RWD",
        "fuel": "Gasoline",
        "transmission": "8AT",
        "body_style": "Coupe",
        "image_url": "https://www.toyota.com/imgix/responsive/images/mlp/colorizer/2024/gr-supra/1L5/1.png"
      },
      {
        "year": 2025,
        "make": "Toyota",
        "model": "GR Corolla",
        "trim": "Core",
        "msrp_usd": 36500,
        "horsepower_hp": 300,
        "drivetrain": "AWD",
        "fuel": "Gasoline",
        "transmission": "6MT",
        "body_style": "Hatchback",
        "image_url": "https://www.toyota.com/imgix/responsive/images/mlp/colorizer/2025/gr-corolla/1L5/1.png"
      },
      {
        "year": 2025,
        "make": "Toyota",
        "model": "Mirai",
        "trim": "XLE (FCEV)",
        "msrp_usd": 49900,
        "horsepower_hp": 182,
        "drivetrain": "RWD",
        "fuel": "Hydrogen Fuel Cell",
        "transmission": "Single-speed",
        "body_style": "Sedan",
        "image_url": "https://www.toyota.com/imgix/responsive/images/mlp/colorizer/2025/mirai/1L5/1.png"
      },
      {
        "year": 2025,
        "make": "Toyota",
        "model": "RAV4",
        "trim": "LE",
        "msrp_usd": 29500,
        "horsepower_hp": 203,
        "drivetrain": "FWD (AWD optional)",
        "fuel": "Gasoline",
        "transmission": "8AT",
        "body_style": "SUV",
        "mpg_combined_est": 30,
        "image_url": "https://www.toyota.com/imgix/responsive/images/mlp/colorizer/2025/rav4/1L5/1.png"
      },
      {
        "year": 2025,
        "make": "Toyota",
        "model": "RAV4 Hybrid",
        "trim": "LE (Hybrid)",
        "msrp_usd": 31475,
        "horsepower_hp": 219,
        "drivetrain": "AWD",
        "fuel": "Hybrid",
        "transmission": "eCVT",
        "body_style": "SUV",
        "mpg_combined_est": 40,
        "image_url": "https://www.toyota.com/imgix/responsive/images/mlp/colorizer/2025/rav4-hybrid/1L5/1.png"
      },
      {
        "year": 2025,
        "make": "Toyota",
        "model": "RAV4 Prime",
        "trim": "SE (PHEV)",
        "msrp_usd": 44800,
        "horsepower_hp": 302,
        "drivetrain": "AWD",
        "fuel": "Plug-in Hybrid",
        "transmission": "eCVT",
        "body_style": "SUV",
        "ev_range_mi_est": 42,
        "image_url": "https://www.toyota.com/imgix/responsive/images/mlp/colorizer/2025/rav4-prime/1L5/1.png"
      },
      {
        "year": 2024,
        "make": "Toyota",
        "model": "Venza",
        "trim": "LE (Hybrid)",
        "msrp_usd": 34700,
        "horsepower_hp": 219,
        "drivetrain": "AWD",
        "fuel": "Hybrid",
        "transmission": "eCVT",
        "body_style": "SUV",
        "image_url": "https://www.toyota.com/imgix/responsive/images/mlp/colorizer/2024/venza/1L5/1.png"
      },
      {
        "year": 2025,
        "make": "Toyota",
        "model": "Highlander",
        "trim": "LE",
        "msrp_usd": 39120,
        "horsepower_hp": 265,
        "drivetrain": "FWD (AWD optional)",
        "fuel": "Gasoline (2.4T)",
        "transmission": "8AT",
        "body_style": "SUV",
        "image_url": "https://www.toyota.com/imgix/responsive/images/mlp/colorizer/2025/highlander/1L5/1.png"
      },
      {
        "year": 2025,
        "make": "Toyota",
        "model": "Highlander Hybrid",
        "trim": "LE (Hybrid)",
        "msrp_usd": 41420,
        "horsepower_hp": 243,
        "drivetrain": "FWD (AWD optional)",
        "fuel": "Hybrid",
        "transmission": "eCVT",
        "body_style": "SUV",
        "image_url": "https://www.toyota.com/imgix/responsive/images/mlp/colorizer/2025/highlander-hybrid/1L5/1.png"
      },
      {
        "year": 2024,
        "make": "Toyota",
        "model": "Grand Highlander",
        "trim": "XLE",
        "msrp_usd": 43970,
        "horsepower_hp": 265,
        "drivetrain": "FWD (AWD optional)",
        "fuel": "Gasoline (2.4T)",
        "transmission": "8AT",
        "body_style": "SUV (3-row)",
        "image_url": "https://www.toyota.com/imgix/responsive/images/mlp/colorizer/2024/grand-highlander/1L5/1.png"
      },
      {
        "year": 2024,
        "make": "Toyota",
        "model": "Grand Highlander Hybrid MAX",
        "trim": "Limited (Hybrid MAX)",
        "msrp_usd": 54475,
        "horsepower_hp": 362,
        "drivetrain": "AWD",
        "fuel": "Hybrid (MAX)",
        "transmission": "6AT (Hybrid MAX)",
        "body_style": "SUV (3-row)",
        "image_url": "https://www.toyota.com/imgix/responsive/images/mlp/colorizer/2024/grand-highlander-hybrid/1L5/1.png"
      },
      {
        "year": 2025,
        "make": "Toyota",
        "model": "4Runner",
        "trim": "SR5",
        "msrp_usd": 40850,
        "horsepower_hp": 278,
        "drivetrain": "RWD (4WD optional)",
        "fuel": "Gasoline (2.4T i-FORCE)",
        "transmission": "8AT",
        "body_style": "SUV (Body-on-frame)",
        "image_url": "https://www.toyota.com/imgix/responsive/images/mlp/colorizer/2025/4runner/1L5/1.png"
      },
      {
        "year": 2025,
        "make": "Toyota",
        "model": "Sequoia",
        "trim": "SR5 (Hybrid)",
        "msrp_usd": 61275,
        "horsepower_hp": 437,
        "drivetrain": "RWD (4WD optional)",
        "fuel": "Hybrid (i-FORCE MAX)",
        "transmission": "10AT",
        "body_style": "SUV (3-row)",
        "image_url": "https://www.toyota.com/imgix/responsive/images/mlp/colorizer/2025/sequoia/1L5/1.png"
      },
      {
        "year": 2024,
        "make": "Toyota",
        "model": "Land Cruiser",
        "trim": "1958",
        "msrp_usd": 55550,
        "horsepower_hp": 326,
        "drivetrain": "4WD",
        "fuel": "Hybrid (i-FORCE MAX 2.4T)",
        "transmission": "8AT",
        "body_style": "SUV",
        "image_url": "https://www.toyota.com/imgix/responsive/images/mlp/colorizer/2024/land-cruiser/1L5/1.png"
      },
      {
        "year": 2024,
        "make": "Toyota",
        "model": "Tacoma",
        "trim": "SR (2.4T)",
        "msrp_usd": 31500,
        "horsepower_hp": 228,
        "drivetrain": "RWD (4x4 optional)",
        "fuel": "Gasoline (2.4T; Hybrid MAX on i-FORCE MAX trims)",
        "transmission": "8AT (6MT avail trims)",
        "body_style": "Midsize Pickup",
        "image_url": "https://www.toyota.com/imgix/responsive/images/mlp/colorizer/2024/tacoma/1L5/1.png"
      },
      {
        "year": 2025,
        "make": "Toyota",
        "model": "Tundra",
        "trim": "SR",
        "msrp_usd": 39965,
        "horsepower_hp": 358,
        "drivetrain": "RWD (4x4 optional)",
        "fuel": "Gasoline (3.4T V6; Hybrid MAX available)",
        "transmission": "10AT",
        "body_style": "Full-size Pickup",
        "image_url": "https://www.toyota.com/imgix/responsive/images/mlp/colorizer/2025/tundra/1L5/1.png"
      },
      {
        "year": 2025,
        "make": "Toyota",
        "model": "bZ4X",
        "trim": "XLE (FWD)",
        "msrp_usd": 43500,
        "horsepower_hp": 201,
        "drivetrain": "FWD (AWD optional 214 hp)",
        "fuel": "Battery Electric",
        "transmission": "Single-speed",
        "body_style": "SUV",
        "ev_range_mi_est": 252,
        "image_url": "https://www.toyota.com/imgix/responsive/images/mlp/colorizer/2025/bz4x/1L5/1.png"
      },
      {
        "year": 2024,
        "make": "Toyota",
        "model": "Sienna",
        "trim": "LE (Hybrid)",
        "msrp_usd": 37000,
        "horsepower_hp": 245,
        "drivetrain": "FWD (AWD optional)",
        "fuel": "Hybrid",
        "transmission": "eCVT",
        "body_style": "Minivan",
        "image_url": "https://www.toyota.com/imgix/responsive/images/mlp/colorizer/2024/sienna/1L5/1.png"
      },
      {
        "year": 2024,
        "make": "Toyota",
        "model": "C-HR (Europe; US = Corolla Cross)",
        "trim": "Corolla Cross L (US)",
        "msrp_usd": 23410,
        "horsepower_hp": 169,
        "drivetrain": "FWD (AWD optional on Hybrid)",
        "fuel": "Gasoline / Hybrid",
        "transmission": "CVT / eCVT",
        "body_style": "SUV",
        "image_url": "https://www.toyota.com/imgix/responsive/images/mlp/colorizer/2024/corolla-cross/1L5/1.png"
      },
      {
        "year": 2025,
        "make": "Toyota",
        "model": "Camry (AWD)",
        "trim": "SE (Hybrid AWD)",
        "msrp_usd": 30700,
        "horsepower_hp": 232,
        "drivetrain": "AWD",
        "fuel": "Hybrid",
        "transmission": "eCVT",
        "body_style": "Sedan",
        "mpg_combined_est": 46,
        "image_url": "https://www.toyota.com/imgix/responsive/images/mlp/colorizer/2025/camry/1L5/1.png"
      }
    ]
  }
  